sinapsis_framework_converter/__init__.py
sinapsis_framework_converter/framework_converter/__init__.py
sinapsis_framework_converter/framework_converter/framework_converter.py
sinapsis_framework_converter/framework_converter/framework_converter_keras_tf.py
sinapsis_framework_converter/framework_converter/framework_converter_tf.py
sinapsis_framework_converter/framework_converter/framework_converter_torch.py
sinapsis_framework_converter/framework_converter/framework_converter_torch_trt.py
sinapsis_framework_converter/framework_converter/framework_converter_trt.py
sinapsis_framework_converter/framework_converter/trt_torch_module_wrapper.py
sinapsis_framework_converter/helpers/__init__.py
sinapsis_framework_converter/helpers/tags.py
sinapsis_framework_converter/templates/__init__.py
sinapsis_framework_converter/templates/framework_converter_base.py
sinapsis_framework_converter/templates/keras_tf_converter_template.py
sinapsis_framework_converter/templates/onnx_trt_converter_template.py
sinapsis_framework_converter/templates/tf_onnx_converter_template.py
sinapsis_framework_converter/templates/torch_onnx_converter.py
sinapsis_framework_converter/templates/torch_trt_converter_template.py
sinapsis_framework_converter-0.1.9.dist-info/licenses/LICENSE
sinapsis_framework_converter-0.1.9.dist-info/METADATA
sinapsis_framework_converter-0.1.9.dist-info/WHEEL
sinapsis_framework_converter-0.1.9.dist-info/top_level.txt
sinapsis_framework_converter-0.1.9.dist-info/RECORD
