Metadata-Version: 2.4
Name: sinapsis-framework-converter
Version: 0.1.9
Summary: Sinapsis tool to convert models from one framework to another and can be used in AOT and JIT modes
Author-email: SinapsisAI <dev@sinapsis.tech>
Project-URL: Homepage, https://sinapsis.tech
Project-URL: Documentation, https://docs.sinapsis.tech/docs
Project-URL: Tutorials, https://docs.sinapsis.tech/tutorials
Project-URL: Repository, https://github.com/Sinapsis-AI/sinapsis-framework-converter.git
Requires-Python: >=3.10
License-File: LICENSE
Requires-Dist: sinapsis>=0.2.1
Requires-Dist: sinapsis-core>=0.2.4
Provides-Extra: tensorflow
Requires-Dist: numpy==1.26.4; extra == "tensorflow"
Requires-Dist: tensorflow>=2.18.0; extra == "tensorflow"
Requires-Dist: tf2onnx>=1.16.1; extra == "tensorflow"
Provides-Extra: onnx
Requires-Dist: onnx>=1.17.0; extra == "onnx"
Requires-Dist: polygraphy>=0.49.9; extra == "onnx"
Provides-Extra: tensorrt
Requires-Dist: torch-tensorrt>=2.4.0; extra == "tensorrt"
Provides-Extra: torch
Requires-Dist: torch>=2.4.1; extra == "torch"
Requires-Dist: torchvision>=0.19.1; extra == "torch"
Provides-Extra: all
Requires-Dist: sinapsis-framework-converter[dev,onnx,tensorflow,tensorrt,torch]; extra == "all"
Dynamic: license-file
